numba_progress/__init__.py
numba_progress/_version.py
numba_progress/numba_atomic.py
numba_progress/progress.py
numba_progress-1.1.3.dist-info/METADATA
numba_progress-1.1.3.dist-info/WHEEL
numba_progress-1.1.3.dist-info/top_level.txt
numba_progress-1.1.3.dist-info/RECORD
