Metadata-Version: 2.2
Name: numba-progress
Version: 1.1.3
Summary: A tqdm-compatible progress bar implementation for numba functions
Author-email: Felix Igelbrink <felix.igelbrink@dfki.de>
License: MIT
Project-URL: Homepage, https://github.com/mortacious/numba-progress
Project-URL: Issues, https://github.com/mortacious/numba-progress/issues
Classifier: Programming Language :: Python :: 3.8
Classifier: Programming Language :: Python :: 3.9
Classifier: Programming Language :: Python :: 3.10
Classifier: Programming Language :: Python :: 3.11
Classifier: Programming Language :: Python :: 3.12
Classifier: License :: OSI Approved :: MIT License
Classifier: Operating System :: POSIX :: Linux
Classifier: Intended Audience :: Developers
Classifier: Topic :: Scientific/Engineering
Classifier: Topic :: Software Development
Requires-Python: >=3.9
Requires-Dist: numba>=0.52
Requires-Dist: numpy
Requires-Dist: tqdm
